{"is_source_file": true, "format": "JavaScript (Node.js)", "description": "Main application setup for an Express.js server, including middleware configuration, route mounting, and Swagger UI integration.", "external_files": ["./routes", "../swagger"], "external_methods": ["cors()", "express()", "routes", "swaggerUi.serve", "swaggerUi.setup"], "published": ["app"], "classes": [], "methods": [{"name": "app.use", "description": "Mounts middleware functions such as CORS, route handlers, Swagger UI, and error handling."}], "calls": ["require('cors')", "require('express')", "require('./routes')", "require('../swagger')", "cors()", "express()", "app.use", "req.get('host')", "req.protocol", "req.socket.localPort", "swaggerUi.setup", "express.json()", "app.use('/', routes)", "console.error", "res.status", "res.json"], "search-terms": ["app.js", "swagger", "CORS setup", "Express middleware", "Swagger UI", "API routing", "error handling middleware"], "state": 2, "file_id": 8, "knowledge_revision": 25, "git_revision": "26e6f93cb06342948897b292bd7b9bbaaf8c06fe", "ctags": [{"_type": "tag", "name": "app", "path": "/home/kavia/workspace/code-generation/quick-to-do-list-54831-54845/backend_api/src/app.js", "pattern": "/^const app = express();$/", "language": "JavaScript", "kind": "constant"}, {"_type": "tag", "name": "cors", "path": "/home/kavia/workspace/code-generation/quick-to-do-list-54831-54845/backend_api/src/app.js", "pattern": "/^const cors = require('cors');$/", "language": "JavaScript", "kind": "constant"}, {"_type": "tag", "name": "express", "path": "/home/kavia/workspace/code-generation/quick-to-do-list-54831-54845/backend_api/src/app.js", "pattern": "/^const express = require('express');$/", "language": "JavaScript", "kind": "constant"}, {"_type": "tag", "name": "routes", "path": "/home/kavia/workspace/code-generation/quick-to-do-list-54831-54845/backend_api/src/app.js", "pattern": "/^const routes = require('.\\/routes');$/", "language": "JavaScript", "kind": "constant"}, {"_type": "tag", "name": "swaggerSpec", "path": "/home/kavia/workspace/code-generation/quick-to-do-list-54831-54845/backend_api/src/app.js", "pattern": "/^const swaggerSpec = require('..\\/swagger');$/", "language": "JavaScript", "kind": "constant"}, {"_type": "tag", "name": "swaggerUi", "path": "/home/kavia/workspace/code-generation/quick-to-do-list-54831-54845/backend_api/src/app.js", "pattern": "/^const swaggerUi = require('swagger-ui-express');$/", "language": "JavaScript", "kind": "constant"}], "hash": "5df3172f6e958a99d255956f667b1de4", "format-version": 4, "code-base-name": "backend_api", "filename": "backend_api/src/app.js", "revision_history": [{"25": "26e6f93cb06342948897b292bd7b9bbaaf8c06fe"}]}